{"version":{"pluginId":"default","version":"current","label":"Next","banner":null,"badge":false,"noIndex":false,"className":"docs-version-current","isLast":true,"docsSidebars":{"docsSidebar":[{"type":"link","href":"/minopamotion/docs/intro","label":"Introduction","docId":"intro","unlisted":false},{"type":"category","label":"Getting Started","items":[{"type":"link","href":"/minopamotion/docs/getting-started/installation","label":"Installation","docId":"getting-started/installation","unlisted":false},{"type":"link","href":"/minopamotion/docs/getting-started/your-first-video","label":"Your First Video","docId":"getting-started/your-first-video","unlisted":false},{"type":"link","href":"/minopamotion/docs/getting-started/project-structure","label":"Project Structure","docId":"getting-started/project-structure","unlisted":false}],"collapsed":true,"collapsible":true},{"type":"category","label":"Concepts","items":[{"type":"link","href":"/minopamotion/docs/concepts/the-fundamentals","label":"The Fundamentals","docId":"concepts/the-fundamentals","unlisted":false},{"type":"link","href":"/minopamotion/docs/concepts/compositions","label":"Compositions","docId":"concepts/compositions","unlisted":false},{"type":"link","href":"/minopamotion/docs/concepts/sequences","label":"Sequences","docId":"concepts/sequences","unlisted":false},{"type":"link","href":"/minopamotion/docs/concepts/animation","label":"Animation","docId":"concepts/animation","unlisted":false},{"type":"link","href":"/minopamotion/docs/concepts/media","label":"Media","docId":"concepts/media","unlisted":false}],"collapsed":true,"collapsible":true},{"type":"category","label":"Player","items":[{"type":"link","href":"/minopamotion/docs/player/overview","label":"Player Overview","docId":"player/overview","unlisted":false},{"type":"link","href":"/minopamotion/docs/player/player-component","label":"Player Component","docId":"player/player-component","unlisted":false},{"type":"link","href":"/minopamotion/docs/player/player-ref","label":"PlayerRef","docId":"player/player-ref","unlisted":false},{"type":"link","href":"/minopamotion/docs/player/thumbnail","label":"Thumbnail","docId":"player/thumbnail","unlisted":false}],"collapsed":true,"collapsible":true},{"type":"category","label":"Rendering","items":[{"type":"link","href":"/minopamotion/docs/rendering/overview","label":"Rendering Overview","docId":"rendering/overview","unlisted":false},{"type":"link","href":"/minopamotion/docs/rendering/server-side","label":"Server-Side Rendering","docId":"rendering/server-side","unlisted":false},{"type":"link","href":"/minopamotion/docs/rendering/client-side","label":"Client-Side Rendering","docId":"rendering/client-side","unlisted":false},{"type":"link","href":"/minopamotion/docs/rendering/cli","label":"CLI","docId":"rendering/cli","unlisted":false}],"collapsed":true,"collapsible":true},{"type":"category","label":"Studio","items":[{"type":"link","href":"/minopamotion/docs/studio/overview","label":"Studio","docId":"studio/overview","unlisted":false}],"collapsed":true,"collapsible":true},{"type":"category","label":"API Reference","items":[{"type":"category","label":"Core","items":[{"type":"link","href":"/minopamotion/docs/api/core/composition","label":"Composition","docId":"api/core/composition","unlisted":false},{"type":"link","href":"/minopamotion/docs/api/core/sequence","label":"Sequence","docId":"api/core/sequence","unlisted":false},{"type":"link","href":"/minopamotion/docs/api/core/absolute-fill","label":"AbsoluteFill","docId":"api/core/absolute-fill","unlisted":false},{"type":"link","href":"/minopamotion/docs/api/core/still","label":"Still","docId":"api/core/still","unlisted":false},{"type":"link","href":"/minopamotion/docs/api/core/freeze","label":"Freeze","docId":"api/core/freeze","unlisted":false},{"type":"link","href":"/minopamotion/docs/api/core/loop","label":"Loop","docId":"api/core/loop","unlisted":false},{"type":"link","href":"/minopamotion/docs/api/core/series","label":"Series","docId":"api/core/series","unlisted":false},{"type":"link","href":"/minopamotion/docs/api/core/img","label":"Img","docId":"api/core/img","unlisted":false},{"type":"link","href":"/minopamotion/docs/api/core/audio","label":"Audio","docId":"api/core/audio","unlisted":false},{"type":"link","href":"/minopamotion/docs/api/core/video","label":"Video","docId":"api/core/video","unlisted":false},{"type":"link","href":"/minopamotion/docs/api/core/use-current-frame","label":"useCurrentFrame()","docId":"api/core/use-current-frame","unlisted":false},{"type":"link","href":"/minopamotion/docs/api/core/use-video-config","label":"useVideoConfig()","docId":"api/core/use-video-config","unlisted":false},{"type":"link","href":"/minopamotion/docs/api/core/use-delay-render","label":"useDelayRender()","docId":"api/core/use-delay-render","unlisted":false},{"type":"link","href":"/minopamotion/docs/api/core/interpolate","label":"interpolate()","docId":"api/core/interpolate","unlisted":false},{"type":"link","href":"/minopamotion/docs/api/core/interpolate-colors","label":"interpolateColors()","docId":"api/core/interpolate-colors","unlisted":false},{"type":"link","href":"/minopamotion/docs/api/core/spring","label":"spring()","docId":"api/core/spring","unlisted":false},{"type":"link","href":"/minopamotion/docs/api/core/measure-spring","label":"measureSpring()","docId":"api/core/measure-spring","unlisted":false},{"type":"link","href":"/minopamotion/docs/api/core/easing","label":"Easing","docId":"api/core/easing","unlisted":false},{"type":"link","href":"/minopamotion/docs/api/core/delay-render","label":"delayRender() / continueRender() / cancelRender()","docId":"api/core/delay-render","unlisted":false},{"type":"link","href":"/minopamotion/docs/api/core/random","label":"random()","docId":"api/core/random","unlisted":false},{"type":"link","href":"/minopamotion/docs/api/core/static-file","label":"staticFile()","docId":"api/core/static-file","unlisted":false}],"collapsed":true,"collapsible":true},{"type":"category","label":"Player","items":[{"type":"link","href":"/minopamotion/docs/api/player/","label":"Player","docId":"api/player/player","unlisted":false},{"type":"link","href":"/minopamotion/docs/api/player/player-ref","label":"PlayerRef","docId":"api/player/player-ref","unlisted":false},{"type":"link","href":"/minopamotion/docs/api/player/thumbnail","label":"Thumbnail","docId":"api/player/thumbnail","unlisted":false}],"collapsed":true,"collapsible":true},{"type":"category","label":"Renderer","items":[{"type":"link","href":"/minopamotion/docs/api/renderer/render-media","label":"renderMedia()","docId":"api/renderer/render-media","unlisted":false},{"type":"link","href":"/minopamotion/docs/api/renderer/render-frames","label":"renderFrames()","docId":"api/renderer/render-frames","unlisted":false},{"type":"link","href":"/minopamotion/docs/api/renderer/stitch-frames-to-video","label":"stitchFramesToVideo()","docId":"api/renderer/stitch-frames-to-video","unlisted":false},{"type":"link","href":"/minopamotion/docs/api/renderer/bundle","label":"bundle()","docId":"api/renderer/bundle","unlisted":false},{"type":"link","href":"/minopamotion/docs/api/renderer/serve","label":"serve()","docId":"api/renderer/serve","unlisted":false}],"collapsed":true,"collapsible":true},{"type":"category","label":"WebCodecs","items":[{"type":"link","href":"/minopamotion/docs/api/webcodecs/render-media-in-browser","label":"renderMediaInBrowser()","docId":"api/webcodecs/render-media-in-browser","unlisted":false}],"collapsed":true,"collapsible":true},{"type":"category","label":"CLI","items":[{"type":"link","href":"/minopamotion/docs/api/cli/render","label":"render","docId":"api/cli/render","unlisted":false},{"type":"link","href":"/minopamotion/docs/api/cli/dev","label":"dev","docId":"api/cli/dev","unlisted":false}],"collapsed":true,"collapsible":true}],"collapsed":true,"collapsible":true}]},"docs":{"api/cli/dev":{"id":"api/cli/dev","title":"dev","description":"Starts a development server with live preview.","sidebar":"docsSidebar"},"api/cli/render":{"id":"api/cli/render","title":"render","description":"Renders a composition to a video file.","sidebar":"docsSidebar"},"api/core/absolute-fill":{"id":"api/core/absolute-fill","title":"AbsoluteFill","description":"A full-screen container that fills its parent using absolute positioning. Supports ref forwarding.","sidebar":"docsSidebar"},"api/core/audio":{"id":"api/core/audio","title":"Audio","description":"Plays audio synchronized to the timeline.","sidebar":"docsSidebar"},"api/core/composition":{"id":"api/core/composition","title":"Composition","description":"Registers a video composition with its configuration. The component renders nothing — it registers via a useEffect side effect.","sidebar":"docsSidebar"},"api/core/delay-render":{"id":"api/core/delay-render","title":"delayRender() / continueRender() / cancelRender()","description":"Low-level API for delaying frame capture until async operations complete.","sidebar":"docsSidebar"},"api/core/easing":{"id":"api/core/easing","title":"Easing","description":"A collection of easing functions for use with interpolate.","sidebar":"docsSidebar"},"api/core/freeze":{"id":"api/core/freeze","title":"Freeze","description":"Freezes the timeline at a specific frame. Children always see the given frame number regardless of the actual current frame.","sidebar":"docsSidebar"},"api/core/img":{"id":"api/core/img","title":"Img","description":"Renders an image with delay render support. The render waits until the image has loaded.","sidebar":"docsSidebar"},"api/core/interpolate":{"id":"api/core/interpolate","title":"interpolate()","description":"Maps an input value from one range to another, with optional easing and extrapolation.","sidebar":"docsSidebar"},"api/core/interpolate-colors":{"id":"api/core/interpolate-colors","title":"interpolateColors()","description":"Interpolates between colors. Supports hex, rgb, and rgba formats.","sidebar":"docsSidebar"},"api/core/loop":{"id":"api/core/loop","title":"Loop","description":"Repeats its children for a specified number of times or indefinitely.","sidebar":"docsSidebar"},"api/core/measure-spring":{"id":"api/core/measure-spring","title":"measureSpring()","description":"Calculates the number of frames a spring animation takes to settle.","sidebar":"docsSidebar"},"api/core/random":{"id":"api/core/random","title":"random()","description":"Deterministic pseudo-random number generator. Given the same seed, always returns the same value.","sidebar":"docsSidebar"},"api/core/sequence":{"id":"api/core/sequence","title":"Sequence","description":"Shifts the timeline for its children. Inside a Sequence, useCurrentFrame() returns 0 at the frame specified by from.","sidebar":"docsSidebar"},"api/core/series":{"id":"api/core/series","title":"Series","description":"Arranges children sequentially in time. Each child plays after the previous one finishes.","sidebar":"docsSidebar"},"api/core/spring":{"id":"api/core/spring","title":"spring()","description":"Physics-based spring animation. Returns a value that animates from from to to.","sidebar":"docsSidebar"},"api/core/static-file":{"id":"api/core/static-file","title":"staticFile()","description":"Returns the path to a file in the public/ directory.","sidebar":"docsSidebar"},"api/core/still":{"id":"api/core/still","title":"Still","description":"A single-frame composition for generating images. Equivalent to a Composition with durationInFrames= and fps={1}.","sidebar":"docsSidebar"},"api/core/use-current-frame":{"id":"api/core/use-current-frame","title":"useCurrentFrame()","description":"Returns the current frame number. Inside a Sequence, the frame is relative to the sequence start.","sidebar":"docsSidebar"},"api/core/use-delay-render":{"id":"api/core/use-delay-render","title":"useDelayRender()","description":"Hook version of delayRender / continueRender. Delays rendering until the returned callback is called.","sidebar":"docsSidebar"},"api/core/use-video-config":{"id":"api/core/use-video-config","title":"useVideoConfig()","description":"Returns the video configuration. Throws if called outside a Composition or Player.","sidebar":"docsSidebar"},"api/core/video":{"id":"api/core/video","title":"Video","description":"Embeds a video synchronized to the timeline.","sidebar":"docsSidebar"},"api/player/player":{"id":"api/player/player","title":"Player","description":"Embeddable React component for previewing Minopamotion videos.","sidebar":"docsSidebar"},"api/player/player-ref":{"id":"api/player/player-ref","title":"PlayerRef","description":"Imperative API for controlling the Player programmatically.","sidebar":"docsSidebar"},"api/player/thumbnail":{"id":"api/player/thumbnail","title":"Thumbnail","description":"Renders a single frame of a video. Useful for previews and galleries.","sidebar":"docsSidebar"},"api/renderer/bundle":{"id":"api/renderer/bundle","title":"bundle()","description":"Bundles the video project into a static site that can be served for rendering.","sidebar":"docsSidebar"},"api/renderer/render-frames":{"id":"api/renderer/render-frames","title":"renderFrames()","description":"Renders individual frames of a composition as images.","sidebar":"docsSidebar"},"api/renderer/render-media":{"id":"api/renderer/render-media","title":"renderMedia()","description":"Renders a composition to a video file.","sidebar":"docsSidebar"},"api/renderer/serve":{"id":"api/renderer/serve","title":"serve()","description":"Starts a local HTTP server to serve a bundled video project.","sidebar":"docsSidebar"},"api/renderer/stitch-frames-to-video":{"id":"api/renderer/stitch-frames-to-video","title":"stitchFramesToVideo()","description":"Combines rendered frames into a video file using FFmpeg.","sidebar":"docsSidebar"},"api/webcodecs/render-media-in-browser":{"id":"api/webcodecs/render-media-in-browser","title":"renderMediaInBrowser()","description":"Renders a composition to a video file in the browser using the WebCodecs API.","sidebar":"docsSidebar"},"concepts/animation":{"id":"concepts/animation","title":"Animation","description":"Minopamotion provides two animation primitives: interpolate for linear/eased animations and spring for physics-based animations.","sidebar":"docsSidebar"},"concepts/compositions":{"id":"concepts/compositions","title":"Compositions","description":"A Composition registers a video with its configuration. It defines what component to render and the video dimensions, fps, and duration.","sidebar":"docsSidebar"},"concepts/media":{"id":"concepts/media","title":"Media","description":"Minopamotion provides components for embedding images, audio, and video that synchronize with the timeline.","sidebar":"docsSidebar"},"concepts/sequences":{"id":"concepts/sequences","title":"Sequences","description":"A Sequence shifts the timeline for its children. It lets you arrange elements in time without manually calculating frame offsets.","sidebar":"docsSidebar"},"concepts/the-fundamentals":{"id":"concepts/the-fundamentals","title":"The Fundamentals","description":"Videos as Pure Functions","sidebar":"docsSidebar"},"getting-started/installation":{"id":"getting-started/installation","title":"Installation","description":"Prerequisites","sidebar":"docsSidebar"},"getting-started/project-structure":{"id":"getting-started/project-structure","title":"Project Structure","description":"Minopamotion is organized as a monorepo with several packages.","sidebar":"docsSidebar"},"getting-started/your-first-video":{"id":"getting-started/your-first-video","title":"Your First Video","description":"This guide walks you through creating a simple video with Minopamotion and previewing it in the browser.","sidebar":"docsSidebar"},"intro":{"id":"intro","title":"Introduction","description":"Minopamotion is a library for creating videos programmatically using React.","sidebar":"docsSidebar"},"player/overview":{"id":"player/overview","title":"Player Overview","description":"The @minopamotion/player package provides an embeddable React component for previewing Minopamotion videos in the browser.","sidebar":"docsSidebar"},"player/player-component":{"id":"player/player-component","title":"Player Component","description":"The Player component renders a Minopamotion video with playback controls.","sidebar":"docsSidebar"},"player/player-ref":{"id":"player/player-ref","title":"PlayerRef","description":"The PlayerRef provides an imperative API for controlling the Player programmatically.","sidebar":"docsSidebar"},"player/thumbnail":{"id":"player/thumbnail","title":"Thumbnail","description":"The Thumbnail component renders a single frame of a video — useful for previews, social cards, or video galleries.","sidebar":"docsSidebar"},"rendering/cli":{"id":"rendering/cli","title":"CLI","description":"The @minopamotion/cli package provides a command-line interface for rendering videos.","sidebar":"docsSidebar"},"rendering/client-side":{"id":"rendering/client-side","title":"Client-Side Rendering","description":"The @minopamotion/webcodecs package renders videos directly in the browser using the WebCodecs API.","sidebar":"docsSidebar"},"rendering/overview":{"id":"rendering/overview","title":"Rendering Overview","description":"Minopamotion provides multiple rendering backends for producing final video files from your compositions.","sidebar":"docsSidebar"},"rendering/server-side":{"id":"rendering/server-side","title":"Server-Side Rendering","description":"The @minopamotion/renderer package renders videos on the server using Puppeteer for frame capture and FFmpeg for encoding.","sidebar":"docsSidebar"},"studio/overview":{"id":"studio/overview","title":"Studio","description":"The Minopamotion Studio is a visual editor for building and previewing videos.","sidebar":"docsSidebar"}}}}